{
  "_meta": {
    "description": "客户看的白话版本说明 (key=commit 短 sha 或版本号 v2.x.x)。Ivan 每次推新版记得来这里加一笔,不然客户收到通知全是「常规更新」。",
    "match_order": [
      "short_sha",
      "version_tag"
    ],
    "fallback_text": "本次是内部优化,不影响现有功能。"
  },
  "v2.10.7": {
    "title": "🔄 重新登录立刻变绿 (之前要等几分钟)",
    "body": "你刚才反馈的:重新登录后账号管理页还显示「🔴 会话已吊销」,要等很久才变回绿色。已修好 — 以后验证码输对那一刻,UI 立刻变绿,预警群也会收到一条「外事号恢复通知」告诉你好了。不用等 tg-monitor 重启 + 巡检。"
  },
  "v2.10.6": {
    "title": "🟢→🔴 账号管理页状态灯修正",
    "body": "你刚才反馈的:账号清了设备但账号管理页还显示绿色 ● ONLINE。这次修好了 — 吊销后那颗灯会变红字「🔴 会话已吊销」,临时网络异常显示黄字「⚠ 检查异常」,跟驾驶舱对齐。"
  },
  "v2.10.5": {
    "title": "🚨 外事号掉线现在一定会通知(不管主开关)",
    "body": "刚才上线的 v2.10.4 漏了一个设计:如果你之前把业务告警主开关关了,连外事号掉线都不会推。这次修好了 — 掉线属于运维故障,不管你有没有关主开关都会推到预警群,让你知道监控挂了。业务告警(关键词/未回复/删除)照旧受主开关控制。"
  },
  "v2.10.4": {
    "title": "🚨 外事号掉线会通知你了",
    "body": "以前如果外事号在 TG 官方 App 被「终止其他会话」或被封禁,系统悄悄失效但 web 还显示运行中,消息全漏掉。现在每 5 分钟自驾检查一次,账号掉了会马上在预警群发「外事号离线预警」,驾驶舱那张账号卡也会变红标「🔴 会话已吊销」。恢复登录后也会发一条「外事号恢复通知」让你知道。"
  },
  "v2.10.3": {
    "title": "🔧 版本号显示修正 + 更新通知零维护",
    "body": "登入页/设置页底部那个小版本号以前写死的(像 v2.6.12 / v2.8.0 那种旧版本),现在自动读最新版本号显示。另外以后 Ivan 推新版不用手动加版本说明了,通知会自动从 commit 标题生成白话标题,你直接看通知就知道这次改了什么。"
  },
  "v2.10.2": {
    "title": "🔒 安全加固(免担心,不用你做什么)",
    "body": "修了一个推送通知会静默报错的问题;忘记密码验证码加了「错 5 次就锁」防暴力猜;每台机器的登入加密密钥改成独立随机生成。升级后你原本登入的网页会要你重新登一次,用原密码就行。"
  },
  "v2.10.1": {
    "title": "🆕 忘记密码也能自己重置",
    "body": "现在登入页多了「忘记密码?」连结。先在账号管理页把你的 Telegram 和管理员账号绑定(私聊 bot 发 /bind 收到的码就行),以后忘记密码时,bot 会私聊发验证码给你,输入就能改新密码。群里人再多也不影响你一个人收码。"
  },
  "v2.10.0": {
    "title": "🎛️ 新增驾驶舱 + 一键升级按钮",
    "body": "登入后顶部多了「驾驶舱」页面,一屏看完所有账号状态 / 今日消息 / 实时预警。设置页右上角加了「检查更新」按钮,有新版直接点一下自动升级(跟命令行跑 update.sh 一样,失败会自动退回)。"
  },
  "v2.9.2": {
    "title": "🧹 小清理",
    "body": "移除之前不小心留在页面上的测试连结,不影响功能。"
  },
  "v2.9.1": {
    "title": "📝 更新通知改白话版",
    "body": "以前推送通知写的是 commit sha 这种技术词,现在改成你看得懂的白话。检查新版的频率从 1 小时调成 6 小时,不会一直打扰,也省 GitHub 额度。"
  },
  "cd5eca1": {
    "title": "🆕 有新版会自动告诉你",
    "body": "以后系统有更新,会自己在预警群里通知你,不用手动查。升级命令也会一起发过来,复制粘贴就行。"
  },
  "4846088": {
    "title": "🔧 中央台接入小修复",
    "body": "修了个小问题:升级后设置页的「中央台接入 Token」有时候是空的。现在会自动生成,进页面就能看到。"
  },
  "ddb4e48": {
    "title": "🛰️ 加了中央台接入接口",
    "body": "在现有版本上预留一个接口,以后如果多部门需要汇总到一个大屏看,可以接上。不影响现有功能,口子越早留越省事。"
  },
  "4060e11": {
    "title": "🛟 升级/回滚保护",
    "body": "升级命令 bash update.sh 加了保护:升级失败会自动退回旧版,不会让你停机。另外新增了 bash rollback.sh,想回退到指定版本一键搞定。"
  },
  "v2.10.8": {
    "title": "v2.10.8",
    "body": "修复: 驾驶舱把刚登入账号误报成死账号\n\n升级:\n`cd /root/tg-monitor-<部门> && ./update.sh`"
  },
  "v2.10.9": {
    "title": "v2.10.9",
    "body": "修复: 驾驶舱 KPI 群安静时误报 0/1\n\n升级:\n`cd /root/tg-monitor-<部门> && ./update.sh`"
  },
  "v2.10.10": {
    "title": "v2.10.10",
    "body": "修复: 账号登入后自动建 Sheet 分页(旧账号自动补)\n\n升级:\n`cd /root/tg-monitor-<部门> && ./update.sh`"
  },
  "v2.10.11": {
    "title": "v2.10.11",
    "body": "优化: 新部门建表后直接有预警分页\n\n升级:\n`cd /root/tg-monitor-<部门> && ./update.sh`"
  },
  "v2.10.12": {
    "title": "v2.10.12",
    "body": "修复: 双击建表会生两个 sheet\n\n升级:\n`cd /root/tg-monitor-<部门> && ./update.sh`"
  },
  "v2.10.13": {
    "title": "v2.10.13",
    "body": "优化: 同 VPS 多部门 HTTPS 共存不再冲突\n\n升级:\n`cd /root/tg-monitor-<部门> && ./update.sh`"
  },
  "v2.10.14": {
    "title": "v2.10.14",
    "body": "修复: 测试 Sheet 通过立刻存 ID + 装前自动清孤儿容器 + HTTPS 默认开\n\n升级:\n`cd /root/tg-monitor-<部门> && ./update.sh`"
  },
  "v2.10.15": {
    "title": "v2.10.15",
    "body": "修复: 批量登录时漏建的账号分页 60 秒内自动补齐\n\n升级:\n`cd /root/tg-monitor-<部门> && ./update.sh`"
  },
  "v2.10.16": {
    "title": "v2.10.16",
    "body": "修复: 自愈巡检补建的分页格式跟登录建的不一致(阉割版)\n\n升级:\n`cd /root/tg-monitor-<部门> && ./update.sh`"
  },
  "v2.10.17": {
    "title": "v2.10.17",
    "body": "修复: 存量阉割版账号分页 60 秒自愈升级成完整模板(消息数据不丢)\n\n升级:\n`cd /root/tg-monitor-<部门> && ./update.sh`"
  },
  "v2.10.18": {
    "title": "v2.10.18",
    "body": "修复: 一键软升级后弹窗阴魂不散(refs 没跟着更新)\n\n升级:\n`cd /root/tg-monitor-<部门> && ./update.sh`"
  },
  "v2.10.19": {
    "title": "v2.10.19",
    "body": "修复: 登录 TG 账号的错误提示改成白话(不再吐 Telethon 英文)\n\n升级:\n`cd /root/tg-monitor-<部门> && ./update.sh`"
  },
  "v2.10.20": {
    "title": "v2.10.20",
    "body": "修复: 升级时遇到 \"container name already in use\" 冲突\n\n升级:\n`cd /root/tg-monitor-<部门> && ./update.sh`"
  },
  "v2.10.21": {
    "title": "v2.10.21",
    "body": "修复: 防御性 import telethon.errors(旧版 Telethon 升级后 web 打不开)\n\n升级:\n`cd /root/tg-monitor-<部门> && ./update.sh`"
  },
  "v2.10.22": {
    "title": "v2.10.22",
    "body": "修复: 升级后自动恢复挂掉的 Caddy(HTTPS 部署不再手动救)\n\n升级:\n`cd /root/tg-monitor-<部门> && ./update.sh`"
  },
  "v2.10.24": {
    "title": "🔧 v2.10.24 系列累计更新(含 4 个小修补)",
    "body": "这版一次升级,拿到后面 4 个补丁的所有改动。修了这些事:\n\n**1. 升级不再撞容器冲突**\n以前升级偶尔会卡在「容器名冲突」报错失败,要手动清。现在自动清,一条命令升级到底。\n\n**2. 账号多时表格不再偶发空白 / 卡死**\n150 个以上账号的客户,以前会偶发表格 B2 / B3 空白,严重时消息写不进表格。现在系统自动放慢对 Google 的读取频率,不再打爆 Google 的限制。\n\n**3. 自动补填预警分页的历史空白**\n之前因为上面那个问题留下来的表格空白,升级后系统会自动扫三个预警分页,用 DB 里的商务人员 / 所属公司回填空栏。客户不用自己动手。\n\n**4. 预警绝不丢行**\n以前 Google 那边卡顿超过 6 秒,那条预警就会「预警群收到通知但表格没这行」永久消失。现在系统会记账,写失败的预警每 60 秒自动补写,直到成功为止。保证零丢失。\n\n**5. 后台升级弹窗修对了**\n之前后台「版本升级」弹窗展示的说明是错版本的,容易让人以为升级内容不对。修好了,之后显示的就是这个版本真正的说明。\n\n**升级一条命令,已登录账号不用重登,新配置默认都是开的,不用改任何东西:**\n`cd /root/tg-monitor-<部门> && ./update.sh`"
  },
  "v2.10.23": {
    "title": "🔧 大修补一波(推荐所有人立即升级)",
    "body": "修复 7 个影响业务的 bug:\n\n1. 表格有时消息写不进去(批量账号配额压力下队列卡住)— 改成按账号分桶,单号卡限额不影响其他号,自动退避恢复\n2. 账号被 TG 官方冻结/封号后 UI 还显示绿色 ONLINE — 加真 API 探测,冻结/封号现在会正确标红\n3. 预警发送失败后当天不再重试 — 改成只认真送达的才去重,失败下次扫描继续重试\n4. 删除消息检测:收到后立刻被删(还没写到 Sheet 上)的消息永远不会标红 — 修掉\n5. 群里两人同时点审核按钮会重复处理 — 加原子抢占\n6. 任意群成员都能点审核按钮 — 加可选 TG ID 白名单(Web 后台设置页可配)\n7. 在账号分页 B2/B3 填了「渠道人员/中心·部门」但推送显示空值 — 表头同步被单账号异常卡住整批中断,加单账号隔离后其他账号同步不再受影响\n\n另:\n- 账号业务字段启动时不再被空值覆盖(填一次就稳定保留)\n- 新增 Sheets 写入积压告警(默认超 500 条堆 10 分钟推 1 次,1 小时冷却)\n\n升级:\n`cd /root/tg-monitor-<部门> && ./update.sh`"
  },
  "v2.10.24.1": {
    "title": "🚨 紧急修复:表格读配额爆 429(账号多的客户必升)",
    "body": "修紧急 bug:账号数多的客户(>100 个)表格分页 B2/B3 显示空白,严重时消息写入也连锁失败。日志大量 `APIError: [429] Quota exceeded for 'Read requests'`。2026-04-22 某客户线上反馈。\n\n**根因**:\n- 表头同步(sync_headers)和广告主名一致性巡检每 60 秒跑一次,每个账号要读 2-3 次 Sheets\n- 150 账号 × 3 读 / 60 秒 = 450 读/分钟,远超 Google 读配额(60 读/分钟/用户)\n- 连锁把消息实时写入也 429 掉 → 消息丢失\n\n**修复**:\n- 表头同步从每 60 秒降到每 10 分钟(配置化 `SYNC_HEADERS_INTERVAL_SEC`,默认 600s)\n- 广告主名一致性巡检从 60 秒改 10 分钟(配置化 `PEER_NAME_CONSISTENCY_INTERVAL_SEC`,默认 600s,跟原 docstring 对齐)\n- 加紧急开关 `SYNC_HEADERS_DISABLED` / `PEER_NAME_CONSISTENCY_DISABLED`,未来遇到配额问题可一键关\n\n**副作用(极小)**:\n- 手改 B2/B3 或第 6 行的值,同步到 DB 最多延迟 10 分钟(原 60 秒)\n- 实际业务影响可忽略 — 客户一般改完不会立刻期望秒级生效\n\n**如果你刚手动 sed 止血过**:升级自动覆盖 tasks.py 上的止血改动,恢复正常逻辑(但用新 10 分钟间隔,不会再爆配额)\n\n升级:\n`cd /root/tg-monitor-<部门> && ./update.sh`"
  },
  "v2.10.24.2": {
    "title": "🧹 自动补填预警分页历史空白(承接 v2.10.24.1)",
    "body": "承接 v2.10.24.1,修之前止血期间留下的历史脏数据:\n\n**背景**:\nv2.10.24.1 之前因表头同步被卡住 / sed 止血,期间新登录外事号在分页 B2(商务人员)/ B3(所属公司)填的值没同步到系统 DB。客户在看三个预警分页(关键词监听、信息未回复、信息删除)时会看到 A 栏(所属公司)/ B 栏(商务人员)一大片空白 — 就是那段时间命中的告警。\n\n**修复**:\n- 容器启动时立即扫三个预警分页,用 DB 里 accounts 的 `operator` / `company` 回填空栏\n- 新增 `_alert_backfill_loop` 每小时巡检一次,补新命中但一开始 DB 还没 operator 的行\n- 幂等 — 只填空栏,有值的不动,跑多少次都安全\n- 找不到 DB 值的外事号会在日志列出清单,客户去对应外事号分页 B2/B3 填好 → 等 10 分钟下一轮自动补\n\n**配额**:每轮 ~7 次 API 调用,远低于 60/min 配额\n\n**新配置**(默认开):\n- `BACKFILL_ALERT_HISTORY=true`(默认)→ 设 false 可关\n- `BACKFILL_ALERT_INTERVAL_SEC=3600`(默认 1 小时)\n\n**升级后**:\n- 重启立刻补 90%+ 历史空白\n- 之后每小时自动补漏\n- 客户只看表格就好,不用动任何配置\n\n升级:\n`cd /root/tg-monitor-<部门> && ./update.sh`"
  },
  "v2.10.24.3": {
    "title": "🛡️ 预警分页零丢失保障(承接 v2.10.24.2)",
    "body": "承接 v2.10.24.2,修预警分页「整行缺失」问题:\n\n**背景**:\n三个预警分页(关键词监听 / 未回复 / 删除)的写入过去只重试 3 次、每次间隔 2 秒,总容错只有 6 秒。一旦碰到:\n- 表格读配额爆 429 超过 6 秒(150 账号客户已发生)\n- 网络短暂抖动\n- worksheet 短暂不可达\n\n该条预警就会**永久消失** — 客户视角「预警群收到通知,但表格没这一行」。消息分页早在 v2.10.23 就有「sheet_written 标记 + 无限重试」机制保零丢,但预警分页是同机制的盲区。\n\n**修复(类比 messages.sheet_written 模式)**:\n- DB `alerts` 表加 `sheet_written` 标记位,写失败保留 0\n- 新增 `_alert_writeback_loop` 每 60 秒扫一次 `sheet_written=0` 的预警 → 自动补写到分页 → 成功标 1\n- **无限重试**直到成功(配额爆自动退避整轮,下一轮继续)\n- 幂等:标 1 后不再重写,不会产生重复行\n- 历史预警(升级前)一刀标 1,不追补 — 只保障升级后新产生的零丢失\n\n**配额**:每轮最多 50 条,间隔 1.5s,每轮 ~75 秒 API 消耗,积压多时分批清理\n\n**新配置**(默认开):\n- `ALERT_WRITEBACK_DISABLED=false`(默认开)→ 设 true 可关\n- `ALERT_WRITEBACK_INTERVAL_SEC=60`(默认 60 秒)\n\n**升级后**:\n- 之后再碰到 429 或短暂抖动,预警分页不会再缺整行\n- 客户一样不需要改任何配置\n\n升级:\n`cd /root/tg-monitor-<部门> && ./update.sh`"
  },
  "v2.10.24.4": {
    "title": "🩹 修升级说明展示错版本(四段版本号识别)",
    "body": "修 update_checker 展示 bug:客户后台「版本升级」弹窗上显示的升级说明不对,展示的是旧版本的内容。\n\n**背景**:\nupdate_checker 的版本号识别 regex 只匹配三段(如 `v2.10.24`),遇到四段版本号(如 `v2.10.24.3`)会截成三段 → 去 release_notes 里拿到 `v2.10.24` 的旧说明。\n导致:v2.10.24.2 / v2.10.24.3 客户后台升级弹窗都一直显示的是 v2.10.24 的「容器冲突修补」说明,不是真正的新内容。\n\n**修复**:\nregex 从 `v\\d+\\.\\d+\\.\\d+` 改成 `v\\d+(?:\\.\\d+)+`(贪婪吃完所有连续数字段),四段/更多段版本号都能正确识别到 release_notes key。\n\n**影响**:\n- 纯展示层修复,没动业务逻辑\n- 升级后下次客户后台「版本升级」弹窗会显示正确的版本说明\n- 不影响已登录账号 / 不改数据库\n\n升级:\n`cd /root/tg-monitor-<部门> && ./update.sh`"
  },
  "v2.10.24.5": {
    "title": "📝 补旧客户也能看到正确升级说明",
    "body": "配合 v2.10.24.4 — 让还没升上来的老客户,在后台弹窗也能看到完整升级内容。\n\n之前老客户打开后台弹窗会显示过期的版本说明,现在会显示 v2.10.24 系列全部更新内容。\n\n不影响任何功能,打开后台就看得到。\n\n升级:\n`cd /root/tg-monitor-<部门> && ./update.sh`"
  },
  "v2.10.24.6": {
    "title": "📝 后台升级说明文案改白话",
    "body": "把后台「版本升级」弹窗的说明文字改成白话 — 优化了什么 / 解决了什么一看就懂,不再堆技术词(什么 regex / config / SQL 之类的)。\n\n不影响任何功能,纯文案优化。\n\n升级:\n`cd /root/tg-monitor-<部门> && ./update.sh`"
  },
  "v2.10.25": {
    "title": "🔒 新增「TG 档案群存档」模式(设置页可选,默认关,老客户无感)",
    "body": "新增一种图片/文件存放方式,解决个别客户遇到的谷歌账号被冻结问题。\n\n**问题背景**:\n以前外事号收到的图片和文件会存在客户自己的谷歌云端硬盘里。少数情况下对方发来违规内容,谷歌扫到后会冻结客户的谷歌账号,表格也跟着不能写入。\n\n**新方式**:\n图片和文件改成由 bot 转发到一个独立的 TG 群做存档,表格里只写「图片 #编号」「文件 #编号」带超链接,点一下就跳到档案群看原图/下载。违规内容不再落到谷歌那边,谷歌账号就不会被冻结。\n\n**本版重点**:\n- 功能默认不开,所有老客户升级后一切照旧,跟今天一模一样\n- 后台设置页多了「媒体存储模式」下拉:谷歌云端(默认)/ TG 档案群 / 关闭,想切换的客户自己选\n- 选了「TG 档案群」会多出一个「档案群 ID」输入框(负数,-100 开头那种)\n- 建群拉 bot 进去,在群里发 /chatid,bot 会回一条消息告诉你这个群的 ID,复制回填即可\n\n**升级一条命令,已登录账号不用重登,没切换就没影响:**\n`cd /root/tg-monitor-<部门> && ./update.sh`"
  },
  "v3.0.8.1": {
    "title": "🔧 v3.0.8 升级看不到按钮的坑根治 + 普通用户不看到管理员按钮",
    "body": "v3.0.8 发出去后客户反馈「我升级了但看不到深度诊断按钮」。这版根治。\n\n**两个问题一次修**:\n\n**1. 看不到按钮的坑(根治)**\n之前升级时 templates 文件夹是用「目录复制」方式同步到容器里,镜像里这个目录已存在,结果整个文件夹被复制成嵌套两层,Flask 读到的还是镜像旧版没新按钮。\n这版改成「文件级」逐个复制,以后所有页面/文案改动客户跑 update.sh 后自动生效,不用再让运维 docker exec 手动同步。\n\n**2. 普通用户不再看到管理员按钮**\n之前任何登录账号都看到「立刻深度诊断」「一键修复」「立刻重启监听器」三个按钮,普通成员点了会报 403 体验差。\n这版改成:管理员账号才看到这些按钮;普通成员看到一行说明「请联系管理员重启监听器」,知道该找谁。\nreauth / 检查 Sheet 等去设置页的链接维持不变(任何登录都能看)。\n\n**升级动作**:\n`cd /root/tg-monitor-<部门> && ./update.sh`\n\n升级后所有人浏览器刷新一下页面就生效。这版之后,客户每次升级新功能都会自动看到,不再有「升级了但看不到」的问题。"
  },
  "v3.0.8": {
    "title": "🚀 Sheet 写入治本 + 卡死一键自助 — 不用再登服务器了",
    "body": "两个客户案例触发的大改:200+ 账号大客户 Sheet 持续撞 Google 限制 1 天没写;另一个客户卡 1 天但 Google 那边显示完全没调用。这版治本两种情况,全程浏览器点几下,不用 SSH。\n\n**1. 写入方式从根本改了**\n以前每写一条要先读一次再写一次(每个对话 2 次 API 调用),200 个账号同时写就远超 Google 限制。新版本改成只追加不读取(每个对话 1 次调用),配上每分钟全局上限 50 次的节流,大客户实测请求量从每分钟 2000 次砍到 50 次以内。\n\n副作用:**客户在表格里手动改/插/删行不会被覆盖了**。以前缓存机制可能写错位置,现在追加自动跟随表格当前末尾。\n\n**2. 「立刻深度诊断」按钮**\nSheet 写入健康卡片右下角加蓝色按钮 → 点开弹窗,后台跑 SQL 查清楚卡在哪个账号 / 哪条孤儿消息 / 哪个对话槽缺失。以前要登服务器跑 sqlite3 查,现在浏览器直接看明细。\n\n**3. 「一键修复」按钮**\n弹窗里检测到孤儿消息(数据库里写不进去那种)/ 缺对话槽(peer.col_group=NULL)→ 自动显示橙色按钮「修复 N 条」。点一下确认,后台批量标已写或自动分配槽位,解开循环。\n\n**4. 「立刻重启监听器」按钮**\n配额限流卡死场景,卡片底部有橙色重启按钮。点一下 5-10 秒重启,所有写入退避清零立刻重试一次。安全限制:只有管理员能点。\n\n**5. 设置页加 2 个高级字段**\n- Sheets 写入间隔(秒):默认 5,撞配额时调 30-60 减压\n- 每分钟最多调用次数:默认 50,大客户更保守可调 30-40\n\n两个字段填了立刻在设置页保存生效,不用 SSH 改 .env。\n\n**6. 诊断关键词收紧**\n以前任何 404 都被误判成「Sheet 不存在」,实际可能是 Drive 上传失败跟 Sheet 没关系。新诊断必须看到 worksheet/spreadsheet 等明确字样才报这个错,假阳性大幅降低。\n\n**升级动作**:\n`cd /root/tg-monitor-<部门> && ./update.sh`\n\n升级后立刻见效:卡死的客户跑完 update.sh 容器自动重启,新代码生效请求量自动降下来,卡片上点几下深度诊断 + 一键修复 + 立刻重启就能彻底救活。"
  },
  "v3.0.7.1": {
    "title": "🆘 驾驶舱加「立刻重启监听器」按钮 (合并到 v3.0.8 一起发)",
    "body": "v3.0.7.1 救命补丁的核心能力(驾驶舱诊断卡片加「立刻重启监听器」按钮)已合并到 v3.0.8 一起发布,客户直接升级 v3.0.8 即可。"
  },
  "v3.0.7": {
    "title": "🔁 重新授权 Google 后,Sheet 写入不用重启监听器就能恢复了",
    "body": "客户反馈:驾驶舱「Sheet 写入健康」红条点「去重新授权」,授权完了 Google 那边显示成功,但 Sheet 还是不写,要登服务器重启监听器才能恢复。\n\n**原因**:之前监听器只在启动时读一次 Google 授权,后台重新授权拿到的新凭证它没自动取用,得 docker restart 才会重新读。\n\n**这版改了什么**:\n1. 监听器在每次写入时自检 — 如果撞到「授权失效」会自动重新读一次最新的授权凭证再继续写,**5-30 秒内积压自动追写完**,不用碰服务器\n2. 即使你绕开后台直接在 Google 控制台改了授权(没经过本系统),监听器下一轮写入照样能识别并恢复,不会卡死等人工\n3. 后台「授权成功」提示改成「Google Sheets 写入将在 5-30 秒内自动恢复」,客户知道在等什么\n4. 顺便把「授权失效」识别词典从两处分散改成单一来源(以后维护一个地方就好,诊断卡片说什么、自愈识别什么完全一致)\n\n**升级动作**:\n`cd /root/tg-monitor-<部门> && ./update.sh`\n\n升级动作本身就会重启监听器读到新凭证,如果你客户现在正卡在「授权了但还是不写」,跑一下 update.sh 就直接救活,不用单独 docker restart。"
  },
  "v3.0.6": {
    "title": "🛠 驾驶舱可以直接看日志了,Sheet 堵了也告诉你原因",
    "body": "给客服和运维省掉 SSH 步骤,驾驶舱加了 3 个实用功能:\n\n**1. 后台直接看容器日志**\n驾驶舱底部展开「日志查看」面板,选要看哪个容器(监听/Web/Caddy),输入关键词过滤,可一键开启自动刷新。以前 HTTPS 出问题 / 预警没推 / Sheet 卡住都要 SSH 登服务器 docker logs 看,现在浏览器里直接搞定。\n\n⚠ 出于安全,只能看本部门自己的容器,VPS 上其他项目(比如别的 bot、别的网站)看不到。\n\n**2. Sheet 堵了会告诉你原因**\n以前驾驶舱「Sheet 写入健康」只显示一个数字(积压 X 条、上次写入 3 小时前),不知道什么问题。\n\n这版加了自动诊断,积压超过 50 条 + 15 分钟没写入时,系统自动扫监听日志识别原因:\n- Google 授权失效 → 红条 + 「去设置页重新授权」按钮\n- 触发 Google 配额限流 → 黄条 + 「系统自愈中 30 分钟内恢复」提示\n- Sheet 不存在/被删 → 红条 + 「检查 Sheet」按钮\n- 其他原因 → 黄条提示待查\n\n**3. 删除消息预警文案自定义入口补齐**\nv3.0.5 做了删除消息预警 @负责人的功能,但忘了在设置页加对应的「删除消息提醒文案」输入框(要改文案还得 SSH 编辑 .env)。这版补上,系统设置页「两段式未回复预警」区块加了第三个 textarea,跟 30/40 分钟文案一起填。\n\n**升级动作**:\n`cd /root/tg-monitor-<部门> && ./update.sh`\n\n三个功能自动生效,零额外配置。"
  },
  "v3.0.5": {
    "title": "🗑 删除消息预警也能 @ 负责人了(跟两段式预警一致)",
    "body": "客户反馈:两段式未回复预警能 @ 负责人,但删除消息预警不行,看起来两种预警的审批体验不统一。这版对齐。\n\n**加了什么**:\n账号配了\"负责人 TG ID\"之后,删除消息预警也会:\n- 自动 @ 该外事号对应的负责人(直接触发 TG 通知)\n- 审核按钮从\"通过 / 拒绝\"换成\"登记违规 / 取消\",跟两段式一致\n- 可选新增一条自定义文案(系统设置 → 删除预警提示文案)\n\n**没配负责人 TG ID 的账号行为不变**:仍然是老的\"通过 / 拒绝\"按钮,无 @,保持完全向后兼容。\n\n**升级动作**:\n`cd /root/tg-monitor-<部门> && ./update.sh`\n\n已经配过两段式的账号零操作自动生效,下一条删除预警就会按新格式推送。"
  },
  "v3.0.4": {
    "title": "📣 两段式预警的 @ 通知修好了(被 @ 的人会真收到 TG 提示)",
    "body": "有客户反馈「商务和负责人都在预警群里,但预警发出时他们的 TG 没收到通知」— 点名字能跳到 profile,但就是不响。这版修好。\n\n**问题原因**:\n之前代码把 @username 强制转成「蓝色可点击的名字」(inline mention)。这种格式 TG 有反垃圾规则:被 @ 的人如果之前没 /start 过这个机器人,TG 不会给他发通知,只是把名字涂蓝而已。\n\n**这版改成**:\n如果你配的是 `@xxx` 用户名(多数人都是这样配的)→ 直接用 `@xxx` 发,TG 原生识别成 @,稳稳触发通知,不需要对方事先 /start 过机器人。\n\n**你需要做什么?**\n啥也不用做,升级就好。账号里已经配的商务 / 负责人 TG 用户名会自动按新方式推送。\n\n`cd /root/tg-monitor-<部门> && ./update.sh`"
  },
  "v3.0.3": {
    "title": "🩺 升级时自动体检和修复 HTTPS(省得你再 SSH 登录折腾)",
    "body": "承接 v3.0.2 的改进 — 把 HTTPS 故障检测从「客户自己跑诊断工具」升级到「升级时自动体检和自愈」,客户啥也不用操作。\n\n**加了什么**:\n跑 `./update.sh` 升级到新版时,脚本会自动:\n1. 识别出**只属于本部门**的 Caddy 容器(不会误伤你同一台 VPS 上的其他项目)\n2. 对比 Caddyfile 在 host 和容器里是否一致\n3. 不一致(历史上手动改过导致)→ 自动 `docker restart` 修复,5-10 秒 HTTPS 短暂中断\n4. 一致 → 啥也不做,无感升级\n\n**安全保证**:\n- 只动跟当前部门直接相关的那一个 Caddy 容器\n- 你 VPS 上跑的其他项目(比如另一个 bot、另一个网站)一概不碰\n- 容器名不匹配 `tg-caddy-*` 的一律跳过\n\n**升级一条命令,老客户零感知**:\n`cd /root/tg-monitor-<部门> && ./update.sh`"
  },
  "v3.0.2": {
    "title": "🛠 修一台 VPS 部多个部门时 HTTPS 偶尔装不上的问题",
    "body": "如果你在一台 VPS 上同时部了多个部门(比如测试部、正式部、子公司分开跑),这版修好了一个踩了很久的坑。\n\n**问题现象**:\n装第二个、第三个部门时,少数情况装完打不开 HTTPS,浏览器报「无法提供安全连线」。要人工登 VPS 手动搞。\n\n**这版修好了**:\n- 装新部门时自动检测和自愈,装完直接 HTTPS 能用\n- 装失败不再骗你「✅ 安装完成」,会明确告诉你卡在哪一步\n- 新增一条自查命令,一屏看懂你这台 VPS 的 HTTPS 状态(哪些域签下来了 / 哪个部门挂了 / 有没有死站堵队列)\n\n**你需要做什么?**\n啥也不用做,升级就好。功能行为没变,只是把原本会卡的地方修顺了。\n\n`cd /root/tg-monitor-<部门> && ./update.sh`\n\n**HTTPS 有问题时的自查**:\n`bash /root/tg-monitor-<部门>/scripts/caddy-doctor.sh`"
  },
  "v3.0.1": {
    "title": "🛠 两段式按钮默认显示 + 后台版本号修正 + 少量细节",
    "body": "承接 v3.0.0 的小修小补,没开新功能,改善一下使用体验。\n\n**改了什么**:\n- 升级到 v3.0.0 后,账号管理页的「配置两段式」按钮现在会自动显示(之前要去设定页打开一个开关才出现,容易漏)。\n- 驾驶舱和登入页的版本号以前可能显示成老版本(比如升到 v3.0.0 还写 v2.10.x),修好了。\n- 升级时自动同步 README 和升级通知文档到容器(之前个别场景显示老的版本说明)。\n\n**升级一条命令**:\n`cd /root/tg-monitor-<部门> && ./update.sh`"
  },
  "v3.0.0": {
    "title": "🆕 未回复预警升级成两段式(30 分钟 @ 商务,40 分钟 @ 负责人)默认关,老客户无感",
    "body": "新版把「未回复预警」升级成两段式,解决员工 30 分钟没理客户,消息就石沉大海的问题。\n\n**问题背景**:\n以前是客户消息进来 30 分钟没回复,预警群会发一条提醒,然后就没了。如果没人看群,或者商务刚好开会,这条提醒就被盖掉。\n\n**新方式(两段式)**:\n- **第一段(30 分钟)**:员工还没回客户,系统会到预警群 @ 对应的商务人员,带上客户消息原文,温和提醒\n- **第二段(40 分钟,即第一段后再过 10 分钟仍没回)**:自动升级,到预警群 @ 对应的部门负责人,附「登记违规」和「取消」两个按钮\n- 员工只要在外事号里回了客户一条消息,系统立刻结案,不会再发第二段\n- 主管点「登记违规」→ 自动写入违规登记表;点「取消」→ 消息关掉不登记\n\n**本版重点**:\n- 功能默认不开,所有老客户升级后一切照旧,不碰现有行为\n- 后台账号管理页多了「配置两段式」按钮,每个外事号可以设:30 分钟要 @ 的商务 / 40 分钟要 @ 的负责人\n- 文案可以在设定页统一设一次(例如「请尽快回复」「已超过 40 分钟未回复,请处理」),200 个账号不用逐个填 — 特殊账号想单独改也可以\n- @ 人显示对方真名(王小明),不再是蓝字的 @username,一眼看出是谁\n- 未回复预警可以独立发到专用群(设定页填专用群 ID),不跟其他预警混在一起\n\n**装置伪装(一并加的小改动)**:\n外事号 session 以前在 TG 服务器上登记的装置签名是「Telethon」,容易被识别成机器人。这版改成中性签名,降低风控识别的概率 — 客户无需设置,升级自动生效。\n\n**升级一条命令,已登录账号不用重登,没打开两段式开关就跟现在一模一样:**\n`cd /root/tg-monitor-<部门> && ./update.sh`"
  }
}
